LICENSE
MANIFEST.in
README.md
setup.py
tox.ini
genomelink/__init__.py
genomelink/errors.py
genomelink/oauth.py
genomelink.egg-info/PKG-INFO
genomelink.egg-info/SOURCES.txt
genomelink.egg-info/dependency_links.txt
genomelink.egg-info/requires.txt
genomelink.egg-info/top_level.txt
genomelink/resource/__init__.py
genomelink/resource/report.py
tests/__init__.py
tests/test_oauth.py
tests/resource/__init__.py
tests/resource/test_report.py